nonebot_plugin_flash_silentsave/__init__.py
nonebot_plugin_flash_silentsave-1.1.1.dist-info/LICENSE
nonebot_plugin_flash_silentsave-1.1.1.dist-info/METADATA
nonebot_plugin_flash_silentsave-1.1.1.dist-info/WHEEL
nonebot_plugin_flash_silentsave-1.1.1.dist-info/top_level.txt
nonebot_plugin_flash_silentsave-1.1.1.dist-info/RECORD
