Metadata-Version: 2.1
Name: nonebot-plugin-flash-silentsave
Version: 1.1.1
Summary: 静默保存群聊中的闪照
Home-page: https://github.com/KarisAya/nonebot_plugin_flash_silentsave
Author: karisaya
Author-email: 1048827424@qq.com
License: MIT license
Platform: all
License-File: LICENSE
Requires-Dist: nonebot2
Requires-Dist: nonebot-adapter-onebot
